alyvix-3.7.0.data/purelib/alyvix/__init__.py
alyvix-3.7.0.data/purelib/alyvix/core/__init__.py
alyvix-3.7.0.data/purelib/alyvix/core/alyvix_cipher.bat
alyvix-3.7.0.data/purelib/alyvix/core/alyvix_cipher.py
alyvix-3.7.0.data/purelib/alyvix/core/alyvix_robot.bat
alyvix-3.7.0.data/purelib/alyvix/core/alyvix_robot.py
alyvix-3.7.0.data/purelib/alyvix/core/contouring.py
alyvix-3.7.0.data/purelib/alyvix/core/output.py
alyvix-3.7.0.data/purelib/alyvix/core/engine/__init__.py
alyvix-3.7.0.data/purelib/alyvix/core/engine/base.py
alyvix-3.7.0.data/purelib/alyvix/core/engine/image.py
alyvix-3.7.0.data/purelib/alyvix/core/engine/rectangle.py
alyvix-3.7.0.data/purelib/alyvix/core/engine/text.py
alyvix-3.7.0.data/purelib/alyvix/core/engine/tessdata/COPYING
alyvix-3.7.0.data/purelib/alyvix/core/engine/tessdata/deu.traineddata
alyvix-3.7.0.data/purelib/alyvix/core/engine/tessdata/deu_frak.traineddata
alyvix-3.7.0.data/purelib/alyvix/core/engine/tessdata/eng.cube.bigrams
alyvix-3.7.0.data/purelib/alyvix/core/engine/tessdata/eng.cube.fold
alyvix-3.7.0.data/purelib/alyvix/core/engine/tessdata/eng.cube.lm
alyvix-3.7.0.data/purelib/alyvix/core/engine/tessdata/eng.cube.nn
alyvix-3.7.0.data/purelib/alyvix/core/engine/tessdata/eng.cube.params
alyvix-3.7.0.data/purelib/alyvix/core/engine/tessdata/eng.cube.size
alyvix-3.7.0.data/purelib/alyvix/core/engine/tessdata/eng.cube.word-freq
alyvix-3.7.0.data/purelib/alyvix/core/engine/tessdata/eng.tesseract_cube.nn
alyvix-3.7.0.data/purelib/alyvix/core/engine/tessdata/eng.traineddata
alyvix-3.7.0.data/purelib/alyvix/core/engine/tessdata/fra.cube.bigrams
alyvix-3.7.0.data/purelib/alyvix/core/engine/tessdata/fra.cube.fold
alyvix-3.7.0.data/purelib/alyvix/core/engine/tessdata/fra.cube.lm
alyvix-3.7.0.data/purelib/alyvix/core/engine/tessdata/fra.cube.nn
alyvix-3.7.0.data/purelib/alyvix/core/engine/tessdata/fra.cube.params
alyvix-3.7.0.data/purelib/alyvix/core/engine/tessdata/fra.cube.size
alyvix-3.7.0.dist-info/LICENSE
alyvix-3.7.0.dist-info/METADATA
alyvix-3.7.0.dist-info/WHEEL
alyvix-3.7.0.dist-info/top_level.txt
alyvix-3.7.0.dist-info/RECORD
