Metadata-Version: 2.1
Name: alyvix
Version: 3.7.0
Summary: UNKNOWN
Home-page: UNKNOWN
License: GPL V3
Platform: UNKNOWN
License-File: LICENSE
Requires-Dist: cffi==1.14.6
Requires-Dist: greenlet==2.0.2
Requires-Dist: Flask==2.3.2
Requires-Dist: Pillow==8.3.2
Requires-Dist: cefpython3==66.1
Requires-Dist: numpy==1.21.2
Requires-Dist: opencv-python==4.5.3.56
Requires-Dist: pywin32==301
Requires-Dist: gevent==23.7.0
Requires-Dist: psutil==5.8.0
Requires-Dist: nats-python==0.8.0
Requires-Dist: pycryptodomex==3.10.4
Requires-Dist: requests==2.26.0
Requires-Dist: SQLAlchemy==1.4.25
Requires-Dist: psycopg2-binary==2.9.7
Requires-Dist: SQLAlchemy-Utils==0.37.8
Requires-Dist: python-dateutil==2.8.2
Requires-Dist: Flask-Cors==4.0.0
Requires-Dist: simplejson==3.17.5
Requires-Dist: cryptography==37.0.4
Requires-Dist: PyJWT==2.4.0
Requires-Dist: jsonpath-ng==1.5.3
Requires-Dist: opentelemetry-api==1.30.0
Requires-Dist: opentelemetry-sdk==1.30.0
Requires-Dist: opentelemetry-exporter-otlp-proto-http==1.30.0
